{"/N5aF7gR216Q90RN/Csm8g==":"frame-49.png","uNg/rZsnrfBzlQY/r+g6mg==":"mae-mu-xtrl02zuzxe-unsplash.jpg","3LVnfsLx8kl6oxYj7rpjDA==":"kevin-cloney-2zak5fp-p3o-unsplash.jpg","Yn09DldbgJ/yjp8iXxTHkg==":"pawel-czerwinski-ywiowhvrbvu-unsplash.jpg","s7EhEEN2by/KVCWK/ZmJ8w==":"daniela-diaz-u0lqnabx2he-unsplash.jpg","pdEiofDqWPvrDZftBf7OeQ==":"milad-fakurian-wnshbf-btbo-unsplash.jpg","djb2qbT3QKn2F7AdMAmIFQ==":"creator-2.png","w870wSnM/Do1YUrTkQMqWQ==":"creator-1.png","0OIw3RC0u73LGSNHIvk/vw==":"creator-portfolio.png","cAMx4wQJ+rh7UzXBdez6Sw==":"leilani-angel-k84vnnzxmtq-unsplash-cr.jpg","+ASp0Q6eoQGu26QQOA8SvQ==":"simon-lee-ynmpy1mlwms-unsplash.jpeg","WiQ59BGKzCyvdpq4JhEfPQ==":"milad-fakurian-pjg-sxdkpwq-unsplash-cr.jpg","+NQf6rEl6/eoTPi93iEj9A==":"milad-fakurian-bmsa5-tlfao-unsplash.jpg","yb6xHVi4NWTdV+D5N/SUKA==":"pawel-czerwinski-5kbadjivruc-unsplash1.jpg","XZ0x/sVOY2qDFMeipJyijA==":"gallery1.jpg","Lf/WoVi5L3Qnp6b23+MiVQ==":"gallery2.jpg","9F2RI94x1lAYvHz8QWyhHg==":"gallery3.jpg","xG7DVvXBC1Fmf5QXEl1FSA==":"gallery4.jpg","RiI4xwAZbTgeiHYklAjRhQ==":"gallery5.jpg","oxHqLzMeFvuCE9s/7onulw==":"gallery6.jpg","YQmv+gmgkTMVfi5ltjpaQA==":"gallery7.jpg","+dY6x6tL4GrzFaK5K1Ldiw==":"gallery8.jpg","sb1ebvdGD6YjhV3q5LcXDQ==":"logo1.png","XzvYanrvNf6uV5iBsDaqhA==":"logo2.png","k3Kh7npmUp7c3OImhp6I2A==":"leilani-angel-k84vnnzxmtq-unsplash-cr-1.jpg","lRbVXvseVorytDA/EIehnw==":"%D0%9F%D0%B5%D0%BD%D1%81%D0%B8%D0%BE%D0%BD%D0%B5%D1%80%20%D0%B7%D0%B0%20%D0%BA%D0%BE%D0%BC%D0%BF%D1%8C%D1%8E%D1%82%D0%B5%D1%80%D0%BE%D0%BC3-259x259.jpg","1KCElQ4RdEntit+jzKBZIw==":"%D0%9F%D0%B5%D0%BD%D1%81%D0%B8%D0%BE%D0%BD%D0%B5%D1%80%20%D0%B7%D0%B0%20%D0%BA%D0%BE%D0%BC%D0%BF%D1%8C%D1%8E%D1%82%D0%B5%D1%80%D0%BE%D0%BC3-259x259.jpeg","26N59xSZgt5cKNVgwNPCvQ==":"%D0%9F%D0%B5%D0%BD%D1%81%D0%B8%D0%BE%D0%BD%D0%B5%D1%80%20%D0%B7%D0%B0%20%D0%BA%D0%BE%D0%BC%D0%BF%D1%8C%D1%8E%D1%82%D0%B5%D1%80%D0%BE%D0%BC3-259x259.jpeg","LVzw1U9zFDC0MPfS61Dk5g==":"image.png-16x25.png","MksBoN3hCk1yhZ4eKqhlkw==":"1png.png-54x80.png","yy9Ln9sMQaE5SHHy3x3eVw==":"1png.png-1-54x80.png","uJtNjTYKKRELfMGbYAAkiA==":"1png.png-2-54x80.png","Egyq7frs6BGviGSgKXAWPg==":"1png.png-3-54x80.png","lPmjo9auqU+Kk29ZWzCesg==":"1png.png-4-54x80.png","m3WnrQO/6lAKoBuHG2gvAA==":"1png.png-5-54x80.png","COIC+zBXGj/kh6ZHqdmuwQ==":"%D0%98%D0%BA%D0%BE%D0%BD%D0%BA%D0%B0%D0%951png-51x76.png","c69x5fxxJt8+JV6IIXNDIw==":"%D0%98%D0%BA%D0%BE%D0%BD%D0%BA%D0%B0%D0%951png-51x76.png","2U3m5E3DgQm1GIE5z7/XCg==":"%D0%98%D0%BA%D0%BE%D0%BD%D0%BA%D0%B0%D0%951png-51x76.png","QW5h8aXUouTQ8DCB7SByjA==":"%D0%98%D0%BA%D0%BE%D0%BD%D0%BA%D0%B0%D0%951png-51x76.png","npvil01zk2DYW2PInLoz1Q==":"%D0%98%D0%BA%D0%BE%D0%BD%D0%BA%D0%B0%D0%951png-51x76.png","dyxNvYDBojPCgk0EHZwLzg==":"%D0%9F%D0%B5%D0%BD%D1%81%D0%B8%D0%BE%D0%BD%D0%B5%D1%80%20%D0%B7%D0%B0%20%D0%BA%D0%BE%D0%BC%D0%BF%D1%8C%D1%8E%D1%82%D0%B5%D1%80%D0%BE%D0%BC3-259x259.jpeg","ilcvCxC7al/7FWeX2YPuGg==":"26-11-2024-2.png-137x123.png","U2UtMYcZPkTTQhD2NhbMXQ==":"-4.jpg-669x965.jpg","kl2+t5IHI8ZBOE9Bi+BCQg==":"image.jpg-317x448.jpg","DUSRH+Na92K0UQbrkP3coQ==":"-.jpg-518x755.jpg","0tA0GsCeiJf1BndBkQogZQ==":"image.jpg-521x601.jpg","aUWk1U6uuM0TZK6Bh+3O+g==":"-3d.jpg-113x173.jpg","mNJONLMhQDVCZWWsl0ek+w==":"3d-250.png-145x218.png","T/BXnGaBHoxsSVvDteWOLQ==":"%D0%A0%D0%B0%D0%B7%D0%BC%D0%B5%D1%80%D0%BD%D0%BE%D1%81%D0%B8%D1%82%D0%B8%D0%9E%D0%BF%D1%82%D0%B8%D0%BC%D0%B8%D0%B7%D0%B0%D1%86%D0%B8%D1%8F%D0%A4%D1%80%D0%BE%D0%BD%D1%82-774x1004.png","7f6DzRbYXFqoFXM6QGO4cA==":"pixso.png-523x712.png","k5vtkbDiSE4BjrZCmoQDeg==":"image.jpg-523x578.jpg","KVnCtv7mTOKj5DnCbMsmWQ==":"pensclub.jpg-523x458.jpg","UjaMzlF+tmfa7wrkoft5Ew==":"-.jpg-523x392.jpg","MN4Nx0jByz+aJhDev9uNWQ==":"pensclub.jpg-523x458.jpeg","B9bheuBV5iw7njZHfXQGpA==":"-.jpg-499x374.jpg","9a96hAXV43kkTNUC1j+buQ==":"pensclub.jpg-595x521.jpg","XxCF429bmp8e9ESe9kzHUQ==":"-.jpg-764x572.jpg","NUzF/VzZK9ACXEjnMzko+A==":"image.jpg-595x336.jpg","c2kIF7GsmDvpLD/fdGSeNg==":"image.jpg-1-595x336.jpg","QTeG5nGfdlyxRYorXnQk/Q==":"image.jpg-1-595x336.jpeg","X1cRwqUa3qf0zPl9m1ACMw==":"image.jpg-2-595x336.jpeg","+b78agXlSvX34iMusDksGQ==":"image.jpg-523x296.jpg","25BkA07iZkFRQ9XFsnODBg==":"image.jpg-523x296.jpeg","g5jNzxaDJNW/UrKNX5VZ1Q==":"image.jpg-1-523x296.jpeg","Pwp8UMf9TtvZvaBjUFSDfQ==":"image.jpg-2-523x296.jpeg","euSkoAK8GPWCKgnXHukHBQ==":"image.jpg-3-523x296.jpeg","vFIlsdVOD/fwLM88WuihJw==":"-.jpg-554x331.jpg","A7/14BksZ3c/x3DyVK3S5w==":"-.jpg-333x199.jpeg","Ml07VdgUNhcKGT7FDunXyg==":"-.jpg-580x329.jpg","M6GrMEE8rwie/Qod1OoN1g==":"-.jpg-580x329.jpeg","hQpFzeG0K7cGo1pYRKyBbA==":"-.jpg-224x282.jpg","xDw+FSqK3BlOa1fZoqm1IA==":"-.jpg-224x134.jpg","+L5nqVs2MelwOu/Ha+JIQA==":"-.jpg-523x392.jpeg","dOgbXVI1vd1sIQR0fpUR3w==":"-.jpg-1-523x392.jpeg","YO4hiB9X916VHHfTt4dAWg==":"-.jpg-2-523x392.jpeg","EWFYlEBFNg2WWSdmXSfVmg==":"-3-.jpg-139x212.jpg","I931jmZ5LMIJrqeVNLhCCw==":"-3.jpg-110x151.jpg","PpIfk+mR21m8V3PtGTcXyg==":"-3.jpg-110x151.jpeg","qYc6MgJ9t1NVG6f0vsihww==":"-3.jpg-1-110x151.jpeg","Wpep6Dw+I2F4uAuYC6Yk0A==":"-3.jpg-180x250.jpg","PjmxhIAJjIfah+uRfVu3+A==":"-3.jpg-180x250.jpeg","0FMdGCt2JoBRRe6TUM85yA==":"-3.jpg-1-180x250.jpeg","rL2kCzxBV1gq68BKdqA/IQ==":"-3.jpg-595x954.jpg","JFVvd1okAnX3Q0kYovtyrg==":"3.jpg-585x777.jpg","SbTtRimQWIYRk2yxlY0kTQ==":"3.jpg-595x595.jpg","ND3j+1AB0iBLuCIXd83LOA==":"13.jpg-595x630.jpg","xE67UcMRqC4dKfkC2lOP/Q==":"-01-.jpg-408x612.jpg","U4UXvPmH/NKCHeSwUC4yow==":"-01-.jpg-408x612.jpeg","9DBCcyWC26uMxuPHWz55AQ==":"excel.jpg-626x424.jpg","RpmLrpZsuuUvkiqcIK3XNg==":"image.jpg-906x604.jpg","gjIebkh73Plo2EVtVo/mSQ==":"image.jpg-710x511.jpg","70Th9dTTrjRAIzbBSYXjaA==":"-3.png-595x595.png","k4iPb2/nF9lHs2p6YXix2w==":"3.png-561x561.png","qtxoIXc2hJm8CbBwJc1YKw==":"image.jpg-128x140.jpg"}